{
  "MATERIAL_50" : ["#fde0dc", "#fce4ec", "#f3e5f5", "ede7f6", "#e8eaf6", "#e7e9fd", "#e1f5fe", "#e0f7fa", "#e0f2f1", "#d0f8ce", "#f1f8e9", "#f9fbe7", "#fffde7", "#fff8e1", "#fff3e0", "#fbe9e7", "#efebe9"],
  "MATERIAL_300" : ["#f36c60", "#f06292", "#ba68c8", "#9575cd", "#7986cb", "#91a7ff", "#4fc3f7", "#4dd0e1", "#4db6ac", "#42bd41", "#aed581", "#dce775", "#fff176", "#ffd54f", "#ffb74d", "#ff8a65"],
  "MATERIAL_500" : ["#e51c23", "#e91e63", "#9c27b0", "#673ab7", "#3f51b5", "#5677fc", "#03a9f4", "#00bcd4", "#009688", "#259b24", "#8bc34a", "#cddc39", "#ffeb3b", "#ffc107", "#ff9800", "#ff5722"],
  "MATERIAL_900" : ["#b0120a", "#880e4f", "#4a148c", "#311b92", "#1a237e", "#2a36b1", "#01579b", "#006064", "#004d40", "#0d5302", "#33691e", "#827717", "#f57f17", "#ff6f00", "#e65100", "#bf360c"],
  "MATERIAL_A200" : ["#ff5177", "#ff4081", "#e040fb", "#7c4dff", "#536dfe", "#6889ff", "#40c4ff", "#18ffff", "#64ffda", "#5af158", "#b2ff59", "#eeff41", "#ffff00", "#ffd740", "#ffab40", "#ff6e40"],
  "MATERIAL_A400" : ["#ff2d6f", "#f50057", "#d500f9", "#651fff", "#3d5afe", "#4d73ff", "#00b0ff", "#00e5ff", "#1de9b6", "#14e715", "#76ff03", "#c6ff00", "#ffea00", "#ffc400", "#ff9100", "#ff3d00"]
}
